jvcore/__init__.py
jvcore/communicator.py
jvcore/config.py
jvcore/exceptions.py
jvcore/query_base.py
jvcore/reasoner_base.py
jvcore/singleton.py
jvcore/skill_base.py
jvcore/speech_to_text_base.py
jvcore/text_to_speech_base.py
jvcore/wakeword_base.py
jvcore/testing/__init__.py
jvcore/testing/test_communicator.py
jvcore-1.0.50.dist-info/licenses/LICENSE
jvcore-1.0.50.dist-info/METADATA
jvcore-1.0.50.dist-info/WHEEL
jvcore-1.0.50.dist-info/top_level.txt
jvcore-1.0.50.dist-info/RECORD
